README.rst
setup.py
sphinxcontrib/__init__.py
sphinxcontrib/manpage.py
sphinxcontrib_manpage.egg-info/PKG-INFO
sphinxcontrib_manpage.egg-info/SOURCES.txt
sphinxcontrib_manpage.egg-info/dependency_links.txt
sphinxcontrib_manpage.egg-info/namespace_packages.txt
sphinxcontrib_manpage.egg-info/not-zip-safe
sphinxcontrib_manpage.egg-info/requires.txt
sphinxcontrib_manpage.egg-info/top_level.txt