Metadata-Version: 1.1
Name: sphinxcontrib-manpage
Version: 0.3
Summary: Sphinx linux manpage extension
Home-page: https://github.com/tdi/sphinxcontrib-manpage
Author: Dariusz Dwornikowski
Author-email: dariusz.dwornikowski@cs.put.poznan.pl
License: Apache Common 2.0
Platform: any
Classifier: Development Status :: 4 - Beta
Classifier: Environment :: Console
Classifier: Environment :: Web Environment
Classifier: Intended Audience :: Developers
Classifier: License :: OSI Approved :: Apache Software License
Classifier: Operating System :: OS Independent
Classifier: Programming Language :: Python
Classifier: Topic :: Documentation
